[
    {
        "word": "batten on someone",
        "definition": "to live well by using someone else's money"
    },
    {
        "word": "coerce",
        "definition": "to persuade someone forcefully to do something that they are unwilling to do"
    },
    {
        "word": "indigent",
        "definition": "very poor"
    },
    {
        "word": "impecunious",
        "definition": "having very little money"
    },
    {
        "word": "hard up",
        "definition": "having very little money"
    },
    {
        "word": "destitute",
        "definition": "without money, food, a home, or possessions"
    },
    {
        "word": "sully",
        "definition": "to spoil something that is pure or someone's perfect reputation"
    },
    {
        "word": "stalemate",
        "definition": "a situation in which neither group involved in an argument can win or get an advantage and no action can be taken"
    },
    {
        "word": "stalwart",
        "definition": "loyal, especially for a long time; able to be trusted"
    },
    {
        "word": "liaison",
        "definition": "communication between people or groups who work with each other"
    },
    {
        "word": "murky",
        "definition": "dark and dirty or difficult to see through"
    },
    {
        "word": "tenuous",
        "definition": "A tenuous connection, idea, or situation is weak and possibly does not exist"
    },
    {
        "word": "condone",
        "definition": "to accept or allow behaviour that is wrong"
    },
    {
        "word": "forebear",
        "definition": "a relative who lived in the past"
    },
    {
        "word": "surreptitious",
        "definition": "done secretly, without anyone seeing or knowing"
    },
    {
        "word": "clandestine",
        "definition": "planned or done in secret, especially describing something that is not officially allowed"
    },
    {
        "word": "precarious",
        "definition": "in a dangerous state because of not being safe or not being held in place firmly"
    },
    {
        "word": "bob",
        "definition": "to move up and down quickly and gently, especially on the surface of water"
    },
    {
        "word": "ASBO",
        "definition": "abbreviation for anti-social behaviour order: an official order that a person must stop behaving in a way that annoys or harms other people"
    },
    {
        "word": "enmity",
        "definition": "a feeling of hate"
    },
    {
        "word": "dismal",
        "definition": "sad and without hope"
    },
    {
        "word": "serendipitous",
        "definition": "happening or found by chance"
    },
    {
        "word": "preposterous",
        "definition": "very silly or stupid"
    },
    {
        "word": "toady",
        "definition": "a person who praises and is artificially pleasant to people in authority, usually in order to get some advantage from them"
    },
    {
        "word": "schmooze",
        "definition": "to talk informally with someone, especially in a way that is not sincere or to win some advantage for yourself"
    },
    {
        "word": "backhanded compliment",
        "definition": "a remark that seems to say something pleasant about a person but could also be an insult"
    },
    {
        "word": "bow and scrape",
        "definition": "to show too much politeness or attention to someone"
    },
    {
        "word": "deference",
        "definition": "respect and politeness"
    },
    {
        "word": "ingratiatingly",
        "definition": "in a way that is intended to make people like you"
    },
    {
        "word": "infatuation",
        "definition": "strong but not usually lasting feelings of love or attraction"
    },
    {
        "word": "intrepid",
        "definition": "extremely brave and showing no fear of dangerous situations"
    },
    {
        "word": "attenuate",
        "definition": "to make something less or weaker"
    },
    {
        "word": "countenance",
        "definition": "the appearance or expression of someone's face"
    },
    {
        "word": "sanguine",
        "definition": "red in colour"
    },
    {
        "word": "sanguine",
        "definition": "(of someone or someone's character) positive and hoping for good things"
    },
    {
        "word": "play fast and loose with something/someone",
        "definition": "to treat something or someone without enough care"
    },
    {
        "word": "skulduggery",
        "definition": "secret and dishonest behaviour"
    },
    {
        "word": "in cahoots (with)",
        "definition": "acting together with others for an illegal or dishonest purpose"
    },
    {
        "word": "cerulean",
        "definition": "deep blue in colour"
    },
    {
        "word": "in high dudgeon",
        "definition": "If you do something in high dudgeon, you do it angrily, usually because of the way you have been treated"
    },
    {
        "word": "commandeer",
        "definition": "to take possession of or control private property by force or for military use"
    },
    {
        "word": "adjure",
        "definition": "to ask or order someone to do something"
    },
    {
        "word": "pivot",
        "definition": "a fixed point supporting something that turns or balances"
    },
    {
        "word": "benign",
        "definition": "pleasant and kind"
    },
    {
        "word": "aberrant",
        "definition": "different from what is typical or usual, especially in an unacceptable way"
    },
    {
        "word": "incongruence",
        "definition": "the state of not being suitable or not fitting well with something else"
    },
    {
        "word": "incongruent",
        "definition": "not suitable or not fitting well with something else"
    },
    {
        "word": "unequivocally",
        "definition": "in a way that is total, or expressed very clearly with no doubt"
    },
    {
        "word": "waver",
        "definition": "to lose strength, determination, or purpose, especially temporarily"
    },
    {
        "word": "avail",
        "definition": "use, purpose, advantage, or profit"
    },
    {
        "word": "allude to someone/something",
        "definition": "to mention someone or something without talking about him, her, or it directly"
    },
    {
        "word": "trove",
        "definition": "a large amount of something good, useful, or valuable, or a place where this can be found"
    },
    {
        "word": "scurry",
        "definition": "to move quickly, with small, short steps"
    },
    {
        "word": "malady",
        "definition": "a disease"
    },
    {
        "word": "strenuous",
        "definition": "needing or using a lot of physical or mental effort or energy"
    },
    {
        "word": "obstinacy",
        "definition": "the quality of being unreasonably determined, especially to act in a particular way and not to change at all, despite what anyone else says"
    },
    {
        "word": "acquiesce",
        "definition": "to accept or agree to something, often unwillingly"
    },
    {
        "word": "languor",
        "definition": "pleasant mental or physical tiredness or lack of activity"
    },
    {
        "word": "lassitude",
        "definition": "physical or mental tiredness"
    },
    {
        "word": "vivacious",
        "definition": "A vivacious person, especially a woman or girl, is attractively energetic and enthusiastic"
    },
    {
        "word": "dogged",
        "definition": "very determined to continue doing something, or trying to do something, even when this is difficult or takes a long time"
    },
    {
        "word": "be on the make",
        "definition": "to be trying very hard to get more money and power"
    },
    {
        "word": "grandiose",
        "definition": "larger and containing more detail than necessary, or intended to seem important or great"
    },
    {
        "word": "grandeur",
        "definition": "the quality of being very large and special or beautiful"
    },
    {
        "word": "percolate",
        "definition": "to spread slowly"
    },
    {
        "word": "cut and thrust",
        "definition": "interesting and exciting arguments"
    },
    {
        "word": "belligerence",
        "definition": "the wish to fight or argue"
    },
    {
        "word": "hassle",
        "definition": "(a situation causing) difficulty or trouble"
    },
    {
        "word": "languorous",
        "definition": "mentally or physically tired or not active, in a way that feels or looks pleasant"
    },
    {
        "word": "listless",
        "definition": "having no energy and enthusiasm and unwilling to do anything needing effort"
    },
    {
        "word": "languid",
        "definition": "moving or speaking slowly with little energy, often in an attractive way"
    },
    {
        "word": "dismally",
        "definition": "in a way that makes you feel very sad and without hope, or that shows someone is sad and without hope"
    },
    {
        "word": "tumultuous",
        "definition": "very loud, or full of confusion, change, or uncertainty"
    },
    {
        "word": "tumult",
        "definition": "a loud noise, especially that produced by an excited crowd, or a state of confusion, change, or uncertainty"
    },
    {
        "word": "pamper",
        "definition": "to give someone special treatment, making that person as comfortable as possible and giving them whatever they want"
    },
    {
        "word": "divulge",
        "definition": "to make something secret known"
    },
    {
        "word": "solemn",
        "definition": "serious and without any humour"
    },
    {
        "word": "amble",
        "definition": "to walk in a slow and relaxed way"
    },
    {
        "word": "saunter",
        "definition": "to walk in a slow and relaxed way, often in no particular direction"
    },
    {
        "word": "notwithstanding",
        "definition": "despite the fact or thing mentioned"
    },
    {
        "word": "forestall",
        "definition": "to prevent something from happening by acting first"
    },
    {
        "word": "snide",
        "definition": "(especially of remarks) containing unpleasant criticism that is not clearly stated"
    },
    {
        "word": "bogus",
        "definition": "false, not real, or not legal"
    },
    {
        "word": "phony",
        "definition": "not sincere or not real"
    },
    {
        "word": "tactile",
        "definition": "related to the sense of touch"
    },
    {
        "word": "scratch around for something",
        "definition": "to look for something that is very difficult to find because it is rare"
    },
    {
        "word": "rinse",
        "definition": "to use water to clean the soap or dirt from something"
    },
    {
        "word": "fissure",
        "definition": "a deep, narrow crack, especially in rock or the earth"
    },
    {
        "word": "gouge",
        "definition": "to dig or cut into something in a rough or violent way"
    },
    {
        "word": "rut",
        "definition": "a deep, narrow mark made in soft ground especially by a wheel"
    },
    {
        "word": "crevice",
        "definition": "a small, narrow crack or space, especially in the surface of rock"
    },
    {
        "word": "thrum",
        "definition": "to make a continuous low sound"
    },
    {
        "word": "susurration",
        "definition": "a soft, low noise like someone whispering (= speaking using their breath but not their voice)"
    },
    {
        "word": "clank",
        "definition": "to make a short loud sound like that of metal objects hitting each other, or to cause something to make this sound"
    },
    {
        "word": "blunder",
        "definition": "a serious mistake, usually caused by not taking care or thinking"
    },
    {
        "word": "lumber",
        "definition": "to move slowly and awkwardly"
    },
    {
        "word": "acumen",
        "definition": "skill in making correct decisions and judgments in a particular subject, such as business or politics"
    },
    {
        "word": "aptitude",
        "definition": "a natural ability or skill"
    },
    {
        "word": "wrangle",
        "definition": "an argument, especially one that continues for a long time"
    },
    {
        "word": "peremptorily",
        "definition": "in a way that expects to be obeyed immediately and without any questions"
    },
    {
        "word": "assert your authority",
        "definition": "to do something to show that you have power over someone or something, or in a particular situation"
    },
    {
        "word": "aggrandize",
        "definition": "to make someone more powerful or important"
    },
    {
        "word": "slather",
        "definition": "to spread something thickly on something else"
    },
    {
        "word": "rambling",
        "definition": "too long and confused"
    },
    {
        "word": "encroach on/upon something",
        "definition": "to gradually take away someone else's rights, or to take control of someone's time, work, etc."
    },
    {
        "word": "dredge",
        "definition": "to remove unwanted things from the bottom of a river, lake, etc. using a boat or special device"
    },
    {
        "word": "dotted around",
        "definition": "to be spread across somewhere"
    },
    {
        "word": "disseminate",
        "definition": "to spread or give out something, especially news, information, ideas, etc., to a lot of people"
    },
    {
        "word": "bedaub",
        "definition": "to cover something very roughly with something sticky or dirty"
    },
    {
        "word": "billow",
        "definition": "to spread over a large area, or (especially of things made of cloth) to become filled with air and appear to be larger"
    },
    {
        "word": "chipper",
        "definition": "very happy"
    },
    {
        "word": "chirpy",
        "definition": "happy and active"
    },
    {
        "word": "swooning",
        "definition": "feeling or expressing a lot of pleasure, love, etc."
    },
    {
        "word": "be full of the joys of spring",
        "definition": "to be very happy"
    },
    {
        "word": "jaunty",
        "definition": "showing that you are happy and confident"
    },
    {
        "word": "chuffed",
        "definition": "pleased or happy"
    },
    {
        "word": "chagrin",
        "definition": "disappointment or anger, especially when caused by a failure or mistake"
    },
    {
        "word": "hubris",
        "definition": "a way of talking or behaving that is too proud"
    },
    {
        "word": "ruminative",
        "definition": "thinking deeply and for a long period"
    },
    {
        "word": "brooding",
        "definition": "making you feel uncomfortable or worried, as if something bad is going to happen"
    },
    {
        "word": "pensive",
        "definition": "thinking in a quiet way, often with a serious expression on your face"
    },
    {
        "word": "poignant",
        "definition": "causing or having a very sharp feeling of sadness"
    },
    {
        "word": "wistful",
        "definition": "sad and thinking about something that is impossible or in the past"
    },
    {
        "word": "angsty",
        "definition": "often worried or unhappy, especially about personal problems"
    },
    {
        "word": "abjection",
        "definition": "the state of being extremely unhappy, poor, unsuccessful, etc."
    },
    {
        "word": "disgruntled",
        "definition": "unhappy, annoyed, and disappointed about something"
    },
    {
        "word": "suss",
        "definition": "to realize, understand, or discover something"
    },
    {
        "word": "assiduity",
        "definition": "great care and attention to detail"
    },
    {
        "word": "assiduous",
        "definition": "showing hard work, care, and attention to detail"
    },
    {
        "word": "painstaking",
        "definition": "extremely careful and correct, and involving a lot of effort"
    },
    {
        "word": "doggedness",
        "definition": "great determination to do something, even if it is very difficult"
    },
    {
        "word": "perseverance",
        "definition": "continued effort to do or achieve something, even when this is difficult or takes a long time"
    },
    {
        "word": "barring",
        "definition": "except if a particular thing happens"
    }
]